setup.py
scripts/stackdriver
stackdriver/__init__.py
stackdriver/client.py
stackdriver/exceptions.py
stackdriver/instance.py
stackdriver.egg-info/PKG-INFO
stackdriver.egg-info/SOURCES.txt
stackdriver.egg-info/dependency_links.txt
stackdriver.egg-info/not-zip-safe
stackdriver.egg-info/requires.txt
stackdriver.egg-info/top_level.txt