Metadata-Version: 1.1
Name: stackdriver
Version: 0.0.0
Summary: A Python client for the Stackdriver service
Home-page: https://github.com/citruspi/py-stackdriver
Author: Mihir Singh (@citruspi)
Author-email: hello@mihirsingh.com
License: UNKNOWN
Platform: any
Classifier: License :: Public Domain
Classifier: Development Status :: 1 - Planning
Classifier: Intended Audience :: Developers
Classifier: Intended Audience :: System Administrators
Classifier: Programming Language :: Python
Classifier: Topic :: Software Development :: Libraries
Classifier: Topic :: System :: Monitoring
Classifier: Operating System :: Unix
Classifier: Operating System :: MacOS :: MacOS X
